README.rst
setup.py
gksol/__about__.py
gksol/__init__.py
gksol/__main__.py
gksol/boards.py
gksol/compiled.pyx
gksol/patterns.py
gksol/plain.py
gksol/reader.py
gksol/render.py
gksol/sparse.py
gksol.egg-info/PKG-INFO
gksol.egg-info/SOURCES.txt
gksol.egg-info/dependency_links.txt
gksol.egg-info/requires.txt
gksol.egg-info/top_level.txt
gksol/gksol_unittests/__init__.py
gksol/gksol_unittests/test_compiled.py
gksol/gksol_unittests/test_mixins.py
gksol/gksol_unittests/test_plain.py
gksol/gksol_unittests/test_sparse.py