Metadata-Version: 1.1
Name: gksol
Version: 0.2.0
Summary: Game of Life Tutorial Implementation and Framework
Home-page: https://github.com/MaineKuehn/gksol
Author: Eileen Kuehn, Max Fischer
Author-email: maxfischer2781@gmail.com
License: MIT
Keywords: gridkaschool tutorial game-of-life gol
Platform: UNKNOWN
Classifier: Development Status :: 4 - Beta
Classifier: License :: OSI Approved :: MIT License
Classifier: Intended Audience :: Education
Classifier: Topic :: Education
Classifier: Programming Language :: Python :: 3 :: Only
Classifier: Programming Language :: Python :: 3.5
Classifier: Programming Language :: Python :: 3.6
Classifier: Programming Language :: Python :: Implementation :: CPython
Classifier: Programming Language :: Python :: Implementation :: PyPy
